intakeinformer/__init__.py
intakeinformer/data/dri_combined.pkl
intakeinformer/data_fetching.py
intakeinformer/data_processing.py
intakeinformer/main_functions.py
intakeinformer/visualization.py
intakeinformer-1.0.0.dist-info/LICENSE
intakeinformer-1.0.0.dist-info/METADATA
intakeinformer-1.0.0.dist-info/WHEEL
intakeinformer-1.0.0.dist-info/RECORD
