Metadata-Version: 2.1
Name: intakeinformer
Version: 1.0.0
Summary: A nutritional tracker warpped around the USDA FoodData Central API. The warpper allows users to track their daily food intake and analyze the nutritional content of their diet based on the USDA food database and their own selections.
Home-page: https://github.com/JunchenX0809/IntakeInformer.git
License: MIT
Author: Junchen Xiong
Requires-Python: >=3.9,<4.0
Classifier: License :: OSI Approved :: MIT License
Classifier: Programming Language :: Python :: 3
Classifier: Programming Language :: Python :: 3.9
Classifier: Programming Language :: Python :: 3.10
Classifier: Programming Language :: Python :: 3.11
Requires-Dist: beautifulsoup4 (>=4.9.3,<5.0.0)
Requires-Dist: matplotlib (>=3.8.2,<4.0.0)
Requires-Dist: numpy (>=1.26.2,<2.0.0)
Requires-Dist: pandas (>=2.1.4,<3.0.0)
Requires-Dist: requests (>=2.31.0,<3.0.0)
Project-URL: Documentation, https://intakeinformer.readthedocs.io
Project-URL: Repository, https://github.com/JunchenX0809/IntakeInformer.git
